vulnerability_checker/__init__.py
vulnerability_checker/__main__.py
vulnerability_checker/checker.py
vulnerability_checker/cli.py
vulnerability_checker/models.py
vulnerability_checker/checks/__init__.py
vulnerability_checker/checks/base.py
vulnerability_checker/checks/code_injection.py
vulnerability_checker/checks/dependency.py
vulnerability_checker/checks/gtk.py
vulnerability_checker/checks/insecure_deserialization.py
vulnerability_checker/checks/secret_leak.py
vulnerability_checker/checks/sql_injection.py
vulnerability_checker/checks/xss.py
vulnerability_checker-0.2.6.dist-info/METADATA
vulnerability_checker-0.2.6.dist-info/WHEEL
vulnerability_checker-0.2.6.dist-info/entry_points.txt
vulnerability_checker-0.2.6.dist-info/top_level.txt
vulnerability_checker-0.2.6.dist-info/RECORD
