Metadata-Version: 2.4
Name: vulnerability-checker
Version: 0.2.6
Summary: Library for detecting vulnerabilities in Python code
Author-email: Damir <damiraminov1@yandex.ru>
License: MIT
Project-URL: Homepage, https://github.com/hecronk/vulnerability-checker
Project-URL: Repository, https://github.com/hecronk/vulnerability-checker
Project-URL: Issues, https://github.com/hecronk/vulnerability-checker/issues
Classifier: Programming Language :: Python :: 3
Classifier: Programming Language :: Python :: 3.8
Classifier: Programming Language :: Python :: 3.9
Classifier: Programming Language :: Python :: 3.10
Classifier: Programming Language :: Python :: 3.11
Classifier: Programming Language :: Python :: 3.12
Classifier: Programming Language :: Python :: 3.13
Classifier: License :: OSI Approved :: MIT License
Classifier: Operating System :: OS Independent
Requires-Python: >=3.8
Requires-Dist: bandit>=1.7.5
Requires-Dist: safety<4.0.0,>=3.5.0
Requires-Dist: rich>=13.5.2
Provides-Extra: dev
